image_processing_sc/__init__.py
image_processing_sc/module1_name/__init__.py
image_processing_sc/module1_name/file1_name.py
image_processing_sc/module1_name/file2_name.py
image_processing_sc/module2_name/__init__.py
image_processing_sc/module2_name/file1_name.py
image_processing_sc/module2_name/file2_name.py
image_processing_sc-0.0.1.dist-info/METADATA
image_processing_sc-0.0.1.dist-info/WHEEL
image_processing_sc-0.0.1.dist-info/top_level.txt
image_processing_sc-0.0.1.dist-info/RECORD
