Metadata-Version: 2.1
Name: image-processing-sc
Version: 0.0.1
Summary: Image Processing Program
Home-page: UNKNOWN
Author: SauloCarvalho
License: UNKNOWN
Platform: UNKNOWN
Requires-Python: >=3.5
Requires-Dist: matplotlib
Requires-Dist: numpy
Requires-Dist: scikit-image (>=0.16.1)
